cpmtokenizer/__init__.py
cpmtokenizer/tokenizer_warper.py
cpmtokenizer-1.0.0.dist-info/METADATA
cpmtokenizer-1.0.0.dist-info/WHEEL
cpmtokenizer-1.0.0.dist-info/top_level.txt
cpmtokenizer-1.0.0.dist-info/RECORD
