Metadata-Version: 2.1
Name: cpmtokenizer
Version: 1.0.0
Summary: Description of your package
Author: Your Name
Author-email: your_email@example.com
